rtl/data_memory.v
`define MEMORY_SIZE 1000

module data_memory(
    input clk,
    input [31:0] addr,
    input [31:0] data_write,
    input enable,
    input read_write,
    output reg [31:0] data_read
);

    reg [31:0] data_memory_array [`MEMORY_SIZE-1:0];

    always@(*) begin
        if (enable & !read_write) begin
            data_read = data_memory_array[addr];
        end
    end

    always@(posedge clk) begin
        if (enable & read_write) begin
            data_memory_array[addr] = data_write;
        end
    end

    initial begin
        $dumpfile("../vcd/data_memory.vcd");
        $dumpvars(0,data_memory);
    end


endmodule

vcd/data_memory.vcd
$date
	Mon Aug  5 20:28:31 2024
$end
$version
	Icarus Verilog
$end
$timescale
	1ps
$end
$scope module data_memory $end
$var wire 32 ! addr [31:0] $end
$var wire 1 " clk $end
$var wire 32 # data_write [31:0] $end
$var wire 1 $ enable $end
$var wire 1 % read_write $end
$var reg 32 & data_read [31:0] $end
$upscope $end
$enddefinitions $end
$comment Show the parameter values. $end
$dumpall
$end
#0
$dumpvars
b10110010001110010000001011011011 &
0%
1$
b101001110100110011100100001100 #
1"
b111111100 !
$end
#500
0"
#1000
1"
#1500
0"
#2000
b101101100101111100011100010101 #
b1011100011 !
1%
1"
#2500
0"
#3000
1"
#3500
0"
#4000
b101101100101111100011100010101 &
0%
1"
#4500
0"
#5000
b11001100010110111001000110101111 &
b11101101110010010110011000011100 #
b100010100 !
1"
#5500
0"
#6000
1"
#6500
0"
#7000
b10010101111110101001001111110011 &
b1000111011110011001010010101101 #
b1000010101 !
1"
#7500
0"
#8000
1"
#8500
0"
#9000
b11110011000001111010101000000100 &
b11111110100100100000110000010100 #
b11010101 !
1"
#9500
0"
#10000
1"
#10500
0"
#11000
b10010111010100010111011000101010 #
b1101100000 !
1%
1"
#11500
0"
#12000
1"
#12500
0"
#13000
b10010111010100010111011000101010 &
0%
1"
#13500
0"
#14000
b1101100001110111111100000011100 #
b100100110 !
1%
1"
#14500
0"
#15000
1"
#15500
0"
#16000
b1101100001110111111100000011100 &
0%
1"
#16500
0"
#17000
b11000000000000100101110110000011 &
b10011101001011101000100011110111 #
b1101100100 !
1"
#17500
0"
#18000
1"
#18500
0"
#19000
b1111111110111110100111110111110 #
b1110110100 !
1%
1"
#19500
0"
#20000
1"
#20500
0"
#21000
b1111111110111110100111110111110 &
0%
1"
#21500
0"
#22000
b1010100000100100011011111000100 #
b101001110 !
1%
1"
#22500
0"
#23000
1"
#23500
0"
#24000
b1010100000100100011011111000100 &
0%
1"
#24500
0"
#25000
b10111111000101110000111100101111 #
b110101100 !
1%
1"
#25500
0"
#26000
1"
#26500
0"
#27000
b10111111000101110000111100101111 &
0%
1"
#27500
0"
#28000
b11100001101110001001101111111011 &
b1010010000110101000110110101011 #
b1100000011 !
1"
#28500
0"
#29000
1"
#29500
0"
#30000
b11110111111110010111010110100000 #
b110001100 !
1%
1"
#30500
0"
#31000
1"
#31500
0"
#32000
b11110111111110010111010110100000 &
0%
1"
#32500
0"
#33000
b10101001110100000011011100000011 &
b10110011100110011010100100001100 #
b10110111 !
1"
#33500
0"
#34000
1"
#34500
0"
#35000
b1000001010101101101010101010010 &
b11000010011111101011111110100 #
b1011011000 !
1"
