rtl/program_counter.v
module program_counter(
    input clk,
    input [31:0] pc,
    output reg [31:0] pc_out
);

    always @(posedge clk) begin
        pc_out <= pc + 4;
    end

initial begin
    $dumpfile("../vcd/program_counter.vcd");
    $dumpvars(0,program_counter);
end

endmodule

vcd/program_counter.vcd
$date
	Mon Aug  5 19:59:32 2024
$end
$version
	Icarus Verilog
$end
$timescale
	1ps
$end
$scope module program_counter $end
$var wire 1 ! clk $end
$var wire 32 " pc [31:0] $end
$var reg 32 # pc_out [31:0] $end
$upscope $end
$enddefinitions $end
$comment Show the parameter values. $end
$dumpall
$end
#0
$dumpvars
b100 #
b0 "
1!
$end
#500
0!
#1000
b1 "
1!
#1500
0!
#2000
b101 #
1!
#2500
0!
#3000
b10 "
1!
#3500
0!
#4000
b110 #
1!
#4500
0!
#5000
b11 "
1!
#5500
0!
#6000
b111 #
1!
#6500
0!
#7000
b100 "
1!
#7500
0!
#8000
b1000 #
1!
#8500
0!
#9000
b101 "
1!
#9500
0!
#10000
b1001 #
1!
#10500
0!
#11000
b110 "
1!
#11500
0!
#12000
b1010 #
1!
#12500
0!
#13000
b111 "
1!
#13500
0!
#14000
b1011 #
1!
