rtl/register_file.v
module register_file(
    input clk,
    input [4:0] read_reg1,
    input [4:0] read_reg2,
    input [4:0] write_reg,
    input [31:0] write_data,
    input read_write,
    output reg [31:0] read_data1,
    output reg [31:0] read_data2
);

    reg [31:0] reg_file [31:0];

    // we should write to reg_file at clock edge
    always@(posedge clk) begin
        if (read_write) begin
            reg_file[write_reg] <= write_data;
        end
    end

     //we should always be able to read rs1 and rs2
    assign read_data1 = reg_file[read_reg1];
    assign read_data2 = reg_file[read_reg2];

    initial begin
        $dumpfile("../vcd/register_file.vcd");
        $dumpvars(0,register_file);
    end

endmodule

vcd/register_file.vcd
$date
	Sun Aug  4 20:26:52 2024
$end
$version
	Icarus Verilog
$end
$timescale
	1ps
$end
$scope module register_file $end
$var wire 1 ! clk $end
$var wire 32 " read_data1 [31:0] $end
$var wire 32 # read_data2 [31:0] $end
$var wire 5 $ read_reg1 [4:0] $end
$var wire 5 % read_reg2 [4:0] $end
$var wire 1 & read_write $end
$var wire 32 ' write_data [31:0] $end
$var wire 5 ( write_reg [4:0] $end
$upscope $end
$enddefinitions $end
$comment Show the parameter values. $end
$dumpall
$end
#0
$dumpvars
bz (
bz '
1&
b10000 %
b0 $
b10011010011110001110010010100000 #
b1000011010110001111110011010111 "
1!
$end
#500
0!
#1000
b11101001100001110111101100110101 #
b10001 %
b100100110000011000011011000 "
b1 $
1!
#1500
0!
#2000
b1011010100110111011000110100010 #
b10010 %
b10110000111000110100011110110110 "
b10 $
1!
#2500
0!
#3000
0&
b101101001110011001100110000111 #
b10011 %
b100010000100100010110001001000 "
b11 $
1!
#3500
0!
#4000
1&
b10100100100110110111000010010110 #
b10100 %
b1101001000000101100110110101110 "
b100 $
1!
#4500
0!
#5000
0&
b101000000000101010101111100 #
b10101 %
b10000100001100001000001110000001 "
b101 $
1!
#5500
0!
#6000
b11001111011100010000110110111100 #
b10110 %
b10110100001001101111101111011100 "
b110 $
1!
#6500
0!
#7000
b11100100101100010010100011011010 #
b10111 %
b11100010111011000110101001011 "
b111 $
1!
#7500
0!
#8000
b1111100110010101101011100010001 #
b11000 %
b10001010011100000000001101010101 "
b1000 $
1!
#8500
0!
#9000
1&
b11011010001110001011010010010 #
b11001 %
b10010001111011101111101001111011 "
b1001 $
1!
#9500
0!
#10000
b1000110001111001111010111110011 #
b11010 %
b1100101000001101010010001101000 "
b1010 $
1!
#10500
0!
#11000
b10101110001110010110011101000001 #
b11011 %
b100101010100100100100001110111 "
b1011 $
1!
#11500
0!
#12000
0&
b1110011010001110101001100101100 #
b11100 %
b1010000001010000110000001110110 "
b1100 $
1!
#12500
0!
#13000
1&
b10010100100011000000111011000111 #
b11101 %
b111101011100110010110101100101 "
b1101 $
1!
#13500
0!
#14000
b100100001111000110100001010010 #
b11110 %
b1000011010101010000000010100110 "
b1110 $
1!
#14500
0!
#15000
0&
b1101101110001000010101101000011 #
b11111 %
b10001111111001100110100100001010 "
b1111 $
1!
#15500
0!
#16000
1!
#16001
b1001000000101010001100101010011 '
b10010100100011000000111011000111 "
b11101 $
b11101 (
#16501
0!
#17001
1!
#17501
0!
#18001
b1010101001110101100111000010010 '
b1111100110010101101011100010001 "
b11000 $
b11000 (
1&
1!
#18501
0!
#19001
b1010101001110101100111000010010 "
1!
#19501
0!
#20001
b11001110001101101011001111000111 '
b10101110001110010110011101000001 "
b11011 $
b11011 (
0&
1!
#20501
0!
#21001
1!
#21501
0!
#22001
b11001110111100110011000100100111 '
b1000110001111001111010111110011 "
b11010 $
b11010 (
1&
1!
#22501
0!
#23001
b11001110111100110011000100100111 "
1!
#23501
0!
#24001
b11110100001110110001000110010 '
b100010000100100010110001001000 "
b11 $
b11 (
1!
#24501
0!
#25001
b11110100001110110001000110010 "
1!
#25501
0!
#26001
b10010111101110010011011001110010 '
b1101101110001000010101101000011 "
b11111 $
b11111 (
1!
#26501
0!
#27001
b10010111101110010011011001110010 "
b10010111101110010011011001110010 #
1!
#27501
0!
#28001
b11010001011100011010101111010011 '
b11001110111100110011000100100111 "
b11010 $
b11010 (
1!
#28501
0!
#29001
b11010001011100011010101111010011 "
1!
#29501
0!
#30001
b100101000100100100010111111010 '
b11100010111011000110101001011 "
b111 $
b111 (
1!
#30501
0!
#31001
b100101000100100100010111111010 "
1!
#31501
0!
#32001
b11001001000010001110010001000001 '
b1000011010110001111110011010111 "
b0 $
b0 (
1!
#32501
0!
#33001
b11001001000010001110010001000001 "
1!
#33501
0!
#34001
b11100010100011110001000110110110 '
b1010101001110101100111000010010 "
b11000 $
b11000 (
0&
1!
#34501
0!
#35001
1!
#35501
0!
#36001
b111100011001011011001000001101 '
b10011010011110001110010010100000 "
b10000 $
b10000 (
1!
#36501
0!
#37001
1!
#37501
0!
#38001
b1110110010100100100010010000111 '
b11010001011100011010101111010011 "
b11010 $
b11010 (
1!
#38501
0!
#39001
1!
#39501
0!
#40001
b1000101000011100011010100100110 '
b10001111111001100110100100001010 "
b1111 $
b1111 (
1!
#40501
0!
#41001
1!
#41501
0!
#42001
b110110000111111001011000111101 '
b10011010011110001110010010100000 "
b10000 $
b10000 (
1!
#42501
0!
#43001
1!
#43501
0!
#44001
b10111010010000101100100110111110 '
b100101010100100100100001110111 "
b1011 $
b1011 (
1!
#44501
0!
#45001
1!
#45501
0!
#46001
b11100101111001001111110100001100 '
b1010101001110101100111000010010 "
b11000 $
b11000 (
1&
1!
#46501
0!
#47001
b11100101111001001111110100001100 "
1!
#47501
0!
#48001
b10110010010111101000110010000110 '
b11100100101100010010100011011010 "
b10111 $
b10111 (
0&
1!
#48501
0!
#49001
1!
#49501
0!
#50001
b1111000101010010111110101100110 '
b10100100100110110111000010010110 "
b10100 $
b10100 (
1&
1!
#50501
0!
#51001
b1111000101010010111110101100110 "
1!
#51501
0!
#52001
b110000110100101100100111110101 '
b1011010100110111011000110100010 "
b10010 $
b10010 (
1!
#52501
0!
#53001
b110000110100101100100111110101 "
1!
#53501
0!
#54001
b11111001010100010111010100111111 '
b10101110001110010110011101000001 "
b11011 $
b11011 (
0&
1!
#54501
0!
#55001
1!
#55501
0!
#56001
b10010110111011000110000110100010 '
b10110000111000110100011110110110 "
b10 $
b10 (
1&
1!
#56501
0!
#57001
b10010110111011000110000110100010 "
1!
#57501
0!
#58001
b1101000110111111010000100100 '
b1010000001010000110000001110110 "
b1100 $
b1100 (
0&
1!
#58501
0!
#59001
1!
#59501
0!
#60001
b1111110011111100001111101000110 '
b11101001100001110111101100110101 "
b10001 $
b10001 (
1!
#60501
0!
#61001
1!
#61501
0!
#62001
b11010000100001101001011011110011 '
b1111000101010010111110101100110 "
b10100 $
b10100 (
1&
1!
#62501
0!
#63001
b11010000100001101001011011110011 "
1!
#63501
0!
#64001
b1100001110101101101001010110011 '
b11110100001110110001000110010 "
b11 $
b11 (
1!
#64501
0!
#65001
b1100001110101101101001010110011 "
1!
#65501
0!
#66001
b1100111100100000001101001001011 '
1!
#66501
0!
#67001
b1100111100100000001101001001011 "
1!
#67501
0!
#68001
b1011110100010010000110001111010 '
b101101001110011001100110000111 "
b10011 $
b10011 (
1!
#68501
0!
#69001
b1011110100010010000110001111010 "
1!
#69501
0!
#70001
b11001101111101111010110100010000 '
b11001111011100010000110110111100 "
b10110 $
b10110 (
0&
1!
#70501
0!
#71001
1!
#71501
0!
#72001
b10010000010111101101001111101100 '
b11010001011100011010101111010011 "
b11010 $
b11010 (
1&
1!
#72501
0!
#73001
b10010000010111101101001111101100 "
1!
#73501
0!
#74001
b11100001100010101010010100100110 '
b10000100001100001000001110000001 "
b101 $
b101 (
1!
#74501
0!
#75001
b11100001100010101010010100100110 "
1!
#75501
0!
#76001
b11001101100101000010010110100011 '
b11100100101100010010100011011010 "
b10111 $
b10111 (
0&
1!
#76501
0!
#77001
1!
#77501
0!
#78001
b110110111110111001001110110 '
b10010000010111101101001111101100 "
b11010 $
b11010 (
1&
1!
#78501
0!
#79001
b110110111110111001001110110 "
1!
